cengal_light-4.0.3.dist-info/METADATA
cengal_light-4.0.3.dist-info/WHEEL
cengal_light-4.0.3.dist-info/top_level.txt
cengal_light-4.0.3.dist-info/RECORD
cengal_light-4.0.3.dist-info/NOTICE
cengal_light-4.0.3.dist-info/LICENSE.md
cengal/system.py
cengal/help_tools.py
cengal/__init__.py
cengal/file_settings_manager/config_manager.py
cengal/file_settings_manager/dir_templates.py
cengal/file_settings_manager/__init__.py
cengal/web_tools/help_tools.py
cengal/web_tools/__init__.py
cengal/web_tools/detect_browsers_host_device_type/__init__.py
cengal/web_tools/detect_browsers_host_device_type/by_http_headers/__init__.py
cengal/web_tools/detect_browsers_host_device_type/by_http_headers/versions/__init__.py
cengal/web_tools/detect_browsers_host_device_type/by_http_headers/versions/v_0/by_http_headers.py
cengal/web_tools/detect_browsers_host_device_type/by_http_headers/versions/v_0/__init__.py
cengal/web_tools/detect_browsers_host_device_type/by_http_headers/versions/v_0/tests/_test__template_submodule.py
cengal/web_tools/detect_browsers_host_device_type/by_http_headers/versions/v_0/tests/__init__.py
cengal/web_tools/detect_browsers_host_device_type/by_http_headers/versions/v_0/compilable/__x__build_config.py
cengal/web_tools/detect_browsers_host_device_type/by_http_headers/versions/v_0/compilable/__init__.py
cengal/web_tools/detect_browsers_host_device_type/by_http_user_agent/__init__.py
cengal/web_tools/detect_browsers_host_device_type/by_http_user_agent/versions/__init__.py
cengal/web_tools/detect_browsers_host_device_type/by_http_user_agent/versions/v_0/by_http_user_agent.py
cengal/web_tools/detect_browsers_host_device_type/by_http_user_agent/versions/v_0/__init__.py
cengal/web_tools/detect_browsers_host_device_type/by_http_user_agent/versions/v_0/tests/_test__template_submodule.py
cengal/web_tools/detect_browsers_host_device_type/by_http_user_agent/versions/v_0/tests/__init__.py
cengal/web_tools/detect_browsers_host_device_type/by_http_user_agent/versions/v_1/by_http_user_agent.py
cengal/web_tools/detect_browsers_host_device_type/by_http_user_agent/versions/v_1/__init__.py
